thumbhash/__about__.py
thumbhash/__init__.py
thumbhash-0.1.2.dist-info/METADATA
thumbhash-0.1.2.dist-info/WHEEL
thumbhash-0.1.2.dist-info/licenses/LICENSE
thumbhash-0.1.2.dist-info/RECORD
