Metadata-Version: 2.1
Name: thumbhash
Version: 0.1.2
Summary: A very compact representation of an image placeholder
Project-URL: Documentation, https://github.com/justinforlenza/thumbhash-py#readme
Project-URL: Issues, https://github.com/justinforlenza/thumbhash-py/issues
Project-URL: Source, https://github.com/justinforlenza/thumbhash-py
Author-email: Justin <justin@forlenza.co>
License-Expression: MIT
License-File: LICENSE
Classifier: Development Status :: 4 - Beta
Classifier: Programming Language :: Python
Classifier: Programming Language :: Python :: 3.7
Classifier: Programming Language :: Python :: 3.8
Classifier: Programming Language :: Python :: 3.9
Classifier: Programming Language :: Python :: 3.10
Classifier: Programming Language :: Python :: 3.11
Classifier: Programming Language :: Python :: Implementation :: CPython
Classifier: Programming Language :: Python :: Implementation :: PyPy
Requires-Python: >=3.7
Provides-Extra: pillow
Requires-Dist: pillow; extra == 'pillow'
